bigdance/__init__.py
bigdance/bigdance_integration.py
bigdance/bracket_analysis.py
bigdance/cbb_brackets.py
bigdance/espn_tc_scraper.py
bigdance/wn_cbb_scraper.py
bigdance-0.3.2.dist-info/licenses/LICENSE
bigdance-0.3.2.dist-info/METADATA
bigdance-0.3.2.dist-info/WHEEL
bigdance-0.3.2.dist-info/top_level.txt
bigdance-0.3.2.dist-info/RECORD
