Metadata-Version: 2.4
Name: bigdance
Version: 0.3.2
Summary: March Madness Bracket Pool Simulator and Analyzer
Author-email: Taylor Firman <tefirman@gmail.com>
Maintainer-email: Taylor Firman <tefirman@gmail.com>
License: MIT License
Project-URL: Homepage, https://taylorfirman.com
Project-URL: Repository, https://github.com/tefirman/bigdance.git
Project-URL: Bug Tracker, https://github.com/tefirman/bigdance/issues
Keywords: college basketball,march madness,bracket,warren nolan,espn,tournament challenge
Classifier: Programming Language :: Python :: 3
Classifier: Programming Language :: Python :: 3.8
Classifier: Programming Language :: Python :: 3.9
Classifier: Programming Language :: Python :: 3.10
Classifier: Programming Language :: Python :: 3.11
Classifier: Programming Language :: Python :: 3.12
Classifier: Programming Language :: Python :: 3.13
Classifier: License :: OSI Approved :: MIT License
Classifier: Operating System :: OS Independent
Requires-Python: >=3.8
License-File: LICENSE
Requires-Dist: numpy
Requires-Dist: pandas
Requires-Dist: beautifulsoup4
Requires-Dist: requests
Requires-Dist: lxml
Requires-Dist: urllib3
Requires-Dist: html5lib
Requires-Dist: seaborn
Requires-Dist: matplotlib
Requires-Dist: scipy
Requires-Dist: selenium
Requires-Dist: webdriver_manager
Provides-Extra: dev
Requires-Dist: pytest>=7.0; extra == "dev"
Requires-Dist: pytest-cov; extra == "dev"
Requires-Dist: black; extra == "dev"
Requires-Dist: isort; extra == "dev"
Requires-Dist: ruff; extra == "dev"
Requires-Dist: pre-commit; extra == "dev"
Dynamic: license-file
